{
    "remotePath": "public_html/waitlist/",
    "host": "www.donkaslab.com",
    "username": "donkasla",
    "password": "Ok9C[Pp0H7;lb0",
    "port": 21,
    "secure": false,
    "protocol": "ftp",
    "uploadOnSave": false,
    "passive": false,
    "debug": false,
    "privateKeyPath": null,
    "passphrase": null,
    "agent": null,
    "allow": [],
    "ignore": [
        "\\.vscode",
        "\\.git",
        "\\.DS_Store",
        "\\error_log",
        "\\.xls",
        "\\.xlsx",
        "vendor",
        "composer*",
        "\\events.json",
        "\\.bak",
        "\\.env",
        "dazismaths*",
        "temp",
        "\\.json"
    ],
    "generatedFiles": {
        "extensionsToInclude": [
            ""
        ],
        "path": ""
    }
}